tango/pyaml/__init__.py
tango/pyaml/attribute.py
tango/pyaml/attribute_list.py
tango/pyaml/attribute_list_read_only.py
tango/pyaml/attribute_read_only.py
tango/pyaml/controlsystem.py
tango/pyaml/device_factory.py
tango/pyaml/initializable_element.py
tango/pyaml/multi_attribute.py
tango/pyaml/tango_pyaml_utils.py
tango_pyaml-0.3.1.dist-info/METADATA
tango_pyaml-0.3.1.dist-info/WHEEL
tango_pyaml-0.3.1.dist-info/licenses/LICENSE
tango_pyaml-0.3.1.dist-info/RECORD
