Metadata-Version: 2.4
Name: tango-pyaml
Version: 0.3.1
Summary: Bridge between Tango and PyAML
Project-URL: Homepage, https://github.com/python-accelerator-middle-layer/tango-pyaml
Project-URL: Documentation, https://python-accelerator-middle-layer.github.io/tango-pyaml/
Project-URL: Repository, https://github.com/python-accelerator-middle-layer/tango-pyaml.git
Maintainer-email: Guillaume PICHON <guillaume.pichon@synchrotron-soleil.fr>
License-File: LICENSE
Keywords: Accelerator,Commissioning,Digital Twin,Operation,Synchrotron,Tango,Tuning
Classifier: Development Status :: 3 - Alpha
Classifier: Intended Audience :: Science/Research
Classifier: Natural Language :: English
Classifier: Programming Language :: Python
Classifier: Programming Language :: Python :: 3 :: Only
Classifier: Programming Language :: Python :: 3.9
Classifier: Programming Language :: Python :: 3.10
Classifier: Programming Language :: Python :: 3.11
Classifier: Programming Language :: Python :: 3.12
Classifier: Topic :: Scientific/Engineering :: Physics
Requires-Python: >=3.9
Requires-Dist: accelerator-middle-layer<=0.1.1
Requires-Dist: pydantic>=2.0
Requires-Dist: pytango>=10.1.1
Provides-Extra: dev
Requires-Dist: ipython; extra == 'dev'
Requires-Dist: mypy; extra == 'dev'
Requires-Dist: pytest; extra == 'dev'
Requires-Dist: pytest-mock; extra == 'dev'
Requires-Dist: ruff; extra == 'dev'
